{
  "current_annotations": {
    "collection": [
      "ALS Knowledge Portal"
    ],
    "contributor": [
      "Cytokinetics, Inc."
    ],
    "creator": [
      "Cytokinetics, Inc."
    ],
    "curationLevel": [
      "Standardized"
    ],
    "dataType": [
      "clinical"
    ],
    "dataset_code": [
      "sdtm_als1002"
    ],
    "disease": [
      "ALS"
    ],
    "keywords": [
      "Amyotrophic Lateral Sclerosis, ALS, CK-2127107, Reldesemtiv, COURAGE-ALS"
    ],
    "participant_count": [
      ""
    ],
    "publisher": [
      "Critical Path Institute"
    ],
    "sameAs": [
      "cpath:1957"
    ],
    "source": [
      "Critical Path Institute"
    ],
    "species": [
      "Homo sapiens"
    ],
    "studyType": [
      "Clinical Trial"
    ],
    "subject": [
      "amyotrophic lateral sclerosis"
    ],
    "title": [
      " A Study to Evaluate the Efficacy and Safety of Reldesemtiv in Patients With ALS (Phase 3) [SDTM]"
    ],
    "url": [
      "https://fair.dap.c-path.org/#/data/datasets/sdtm_als1002"
    ]
  },
  "dataset_type": "ClinicalDataset",
  "merged_annotation_template": {
    "_created_timestamp": "2026-05-29T18:11:23.940882+00:00",
    "_dataset_type": "ClinicalDataset",
    "_schema_source": "https://repo-prod.prod.sagebase.org/repo/v1/schema/type/registered/org.synapse.ampals-clinical-dataset",
    "acknowledgementStatement": [
      ""
    ],
    "alternateName": [
      ""
    ],
    "assessmentTypes": [
      ""
    ],
    "citation": [
      ""
    ],
    "clinicalDomain": [
      ""
    ],
    "cohortType": [
      ""
    ],
    "cohort_count": null,
    "collection": [
      "ALS Knowledge Portal"
    ],
    "contributor": [
      "Cytokinetics, Inc."
    ],
    "creator": [
      "Cytokinetics, Inc."
    ],
    "curationLevel": [
      "Standardized"
    ],
    "dataType": [
      "clinical"
    ],
    "dataset_code": [
      "sdtm_als1002"
    ],
    "datePublished": null,
    "description": "",
    "disease": [
      "ALS"
    ],
    "diseaseSubtype": [
      ""
    ],
    "followUpDuration": null,
    "funder": [
      ""
    ],
    "includedInDataCatalog": "",
    "keywords": [
      "Amyotrophic Lateral Sclerosis, ALS, CK-2127107, Reldesemtiv, COURAGE-ALS"
    ],
    "license": "",
    "participant_count": null,
    "portalRelease": [
      ""
    ],
    "primaryOutcome": "",
    "publisher": [
      "Critical Path Institute"
    ],
    "sameAs": [
      "cpath:1957"
    ],
    "source": [
      "Critical Path Institute"
    ],
    "species": [
      "Homo sapiens"
    ],
    "studyDesign": "",
    "studyType": [
      "Clinical Trial"
    ],
    "study_count": null,
    "subject": [
      "amyotrophic lateral sclerosis"
    ],
    "title": [
      " A Study to Evaluate the Efficacy and Safety of Reldesemtiv in Patients With ALS (Phase 3) [SDTM]"
    ],
    "url": [
      "https://fair.dap.c-path.org/#/data/datasets/sdtm_als1002"
    ],
    "visitSchedule": ""
  },
  "missing_fields": [
    "acknowledgementStatement",
    "alternateName",
    "assessmentTypes",
    "citation",
    "clinicalDomain",
    "cohortType",
    "cohort_count",
    "datePublished",
    "description",
    "diseaseSubtype",
    "followUpDuration",
    "funder",
    "includedInDataCatalog",
    "license",
    "participant_count",
    "portalRelease",
    "primaryOutcome",
    "studyDesign",
    "study_count",
    "visitSchedule"
  ],
  "name": "A Study to Evaluate the Efficacy and Safety of Reldesemtiv in Patients With ALS (Phase 3) (SDTM)",
  "publication_hints": [
    "10.1001/jamaneurol.2025.0241.",
    "10.1002/mus.70150.",
    "10.1080/21678421.2023.2216223.",
    "10.1080/21678421.2025.2523941."
  ],
  "synId": "syn72379205",
  "wiki_pages": [
    {
      "id": "639703",
      "markdown": "\n**Summary:** COURAGE-ALS is a Phase 3, double-blind, randomized, placebo-controlled trial of reldesemtiv in patients aged 18 to 80 with ALS.\n\n**Overall Design:**\n\nThe screening and qualification period for the trial will be no more than 21 days in duration. Approximately 555 eligible ALS patients will be randomized (2:1) to receive the following dose of reldesemtiv or placebo (stratified by riluzole use/non-use and edaravone use/non-use) for the first 24 weeks (double-blind, placebo-controlled period):\n- 300 mg reldesemtiv twice a day for a 600 mg total daily dose (TDD)\n- Placebo twice daily\n\nAt the end of the 24-week double-blind, placebo-controlled period, patients will transition to the active drug period, where all patients will receive the following dose of reldesemtiv for the next 24 weeks:\n- 300 mg reldesemtiv twice a day for a 600 mg TDD for patients who were not down titrated during the 24 weeks of blinded dosing\n- 150 mg reldesemtiv twice a day for a 300 mg TDD for patients who were down titrated during the 24 weeks of blinded dosing\n<details>\n\n<summary>Show More</summary>\n<b>Contact:</b>\n\n- Critical Path Insitute: rdcadap@c-path.org\n\n<b>Publications:</b>\n- Rudnicki SA, Giacomelli E, Herder K, Ingre C, Kupfer S, Malik FI, Meng L, Paganoni S, Schellenberg K, Scirocco E, Simkins T, Wei J, Shefner JM; COURAGE-ALS Study Group. The Use of Durable Medical Equipment in COURAGE-ALS, a Phase 3, Multicentre, Randomized Clinical Trial for ALS. Muscle Nerve. 2026 Apr;73(4):608-614. doi: 10.1002/mus.70150. Epub 2026 Jan 19.\n- Rudnicki SA, Gebrehiwet P, Kupfer S, Malik FI, Meng L, Simkins T, Wei J, Wolff AA, Shefner JM. Participant, site personnel and sponsor perspectives on decentralized trial features in COURAGE-ALS: a randomized clinical trial. Amyotroph Lateral Scler Frontotemporal Degener. 2025 Nov;26(7-8):812-820. doi: 10.1080/21678421.2025.2523941. Epub 2025 Jun 27.\n- Shefner JM, Cudkowicz ME, Genge A, Hardiman O, Al-Chalabi A, Andrews JA, Chio A, Corcia P, Couratier P, de Carvalho M, Heiman-Patterson T, Henderson RD, Ingre C, Johnston W, Ludolph A, Maragakis NJ, Miller TM, Mora JS, Petri S, Simmons Z, van den Berg LH, Zinman L, Kupfer S, Malik FI, Meng L, Simkins TJ, Wei J, Wolff AA, Rudnicki SA; COURAGE-ALS Study Group. Reldesemtiv in Amyotrophic Lateral Sclerosis: Results From the COURAGE-ALS Randomized Clinical Trial. JAMA Neurol. 2025 May 1;82(5):477-485. doi: 10.1001/jamaneurol.2025.0241.\n- Shefner JM, Al-Chalabi A, Andrews JA, Chio A, De Carvalho M, Cockroft BM, Corcia P, Couratier P, Cudkowicz ME, Genge A, Hardiman O, Heiman-Patterson T, Henderson RD, Ingre C, Jackson CE, Johnston W, Lechtzin N, Ludolph A, Maragakis NJ, Miller TM, Mora Pardina JS, Petri S, Simmons Z, Van Den Berg LH, Zinman L, Kupfer S, Malik FI, Meng L, Simkins TJ, Wei J, Wolff AA, Rudnicki SA. COURAGE-ALS: a randomized, double-blind phase 3 study designed to improve participant experience and increase the probability of success. Amyotroph Lateral Scler Frontotemporal Degener. 2023 Aug;24(5-6):523-534. doi: 10.1080/21678421.2023.2216223. Epub 2023 May 30.\n</details>",
      "title": ""
    }
  ]
}